coinfeeds/__init__.py
coinfeeds-0.0.4.dist-info/METADATA
coinfeeds-0.0.4.dist-info/WHEEL
coinfeeds-0.0.4.dist-info/RECORD
