Metadata-Version: 2.1
Name: coinfeeds
Version: 0.0.4
Summary: Add your description here
Author-email: Yevgnen Koh <wherejoystarts@gmail.com>
Requires-Python: >=3.10
Requires-Dist: httpx[socks]>=0.25.0
Requires-Dist: pydantic>=2.3.0
